{
  "code": "000000",
  "message": null,
  "messageDetail": null,
  "data": {
    "catalogs": [
      {
        "catalogId": 48,
        "parentCatalogId": null,
        "icon": "https://public.bnbstatic.com/image/cms/content/body/202505/d3201bf0be35bb246b65a767221410e0.png",
        "catalogName": "New Cryptocurrency Listing",
        "description": null,
        "catalogType": 1,
        "total": 2160,
        "articles": [
          {
            "id": 194971,
            "code": "0e830f621fa1424b8f9315c6e3a49bd5",
            "title": "Binance Futures Will Launch USDC-Margined AVAX Perpetual Contract With Up to 75x Leverage",
            "type": 1,
            "releaseDate": 1710747006169
          },
          {
            "id": 194867,
            "code": "bca0f355cf004367b90d7e48fee3470c",
            "title": "Binance Will List BOOK OF MEME (BOME) with Seed Tag Applied",
            "type": 1,
            "releaseDate": 1710581406588
          },
          {
            "id": 194851,
            "code": "543fca9191ba4f3d937d56035a60699a",
            "title": "Binance Futures Will Launch USDⓈ-M BOME Perpetual Contract With Up to 50x Leverage",
            "type": 1,
            "releaseDate": 1710564310142
          },
          {
            "id": 194632,
            "code": "de48474029954b2bb4c479251dbd6a01",
            "title": "Binance Futures Will Launch USDⓈ-M VANRY Perpetual Contract With Up to 50x Leverage",
            "type": 1,
            "releaseDate": 1710338706348
          },
          {
            "id": 194601,
            "code": "ca4f62fa29c44d778160a60a6a760406",
            "title": "Binance Adds AEVO (AEVO) on Earn, Convert, Margin & Futures",
            "type": 1,
            "releaseDate": 1710327333224
          },
          {
            "id": 194456,
            "code": "043436c6551d4f67bf1565a253039b39",
            "title": "Introducing ether.fi (ETHFI) on Binance Launchpool! Farm ETHFI by Staking BNB and FDUSD",
            "type": 1,
            "releaseDate": 1710253801152
          },
          {
            "id": 194408,
            "code": "7c2462b71eea403e8735731becd0208d",
            "title": "Notice on New Trading Pairs & Trading Bots Services on Binance Spot - 2024-03-13 & 2024-03-14",
            "type": 1,
            "releaseDate": 1710234930148
          },
          {
            "id": 194299,
            "code": "7f840e0a2d964bf2bac08cb421ad88eb",
            "title": "Binance Futures Will Launch METISUSDT and WLDUSDC Perpetual Contracts With Up to 75x Leverage",
            "type": 1,
            "releaseDate": 1710217805954
          },
          {
            "id": 194207,
            "code": "427993711da348d59b910d7142fa5939",
            "title": "Binance Adds Metis (METIS) on Earn, Convert & Margin",
            "type": 1,
            "releaseDate": 1710162035327
          },
          {
            "id": 194176,
            "code": "a73748f501dc48f6ba3d68d724052492",
            "title": "Binance Will List Metis (METIS) with Seed Tag Applied",
            "type": 1,
            "releaseDate": 1710143970976
          },
          {
            "id": 194068,
            "code": "46a0372dab2e496c9e0f164a8c2cc819",
            "title": "Binance Options RFQ Will Launch XRPUSDT Options",
            "type": 1,
            "releaseDate": 1709897109545
          },
          {
            "id": 193917,
            "code": "c5699841e8a749ce9c5f57bc18b5db8f",
            "title": "Binance Adds BNB/JPY, BTC/JPY & ETH/JPY Trading Pairs and Launches Zero-Fee Trading for JPY Spot Trading Pairs",
            "type": 1,
            "releaseDate": 1709787611180
          },
          {
            "id": 193868,
            "code": "ecd5240ac636424a853875d97b53f30a",
            "title": "Notice on New Trading Pairs & Trading Bots Services on Binance Spot - 2024-03-07",
            "type": 1,
            "releaseDate": 1709725251502
          },
          {
            "id": 193841,
            "code": "3ff4cb81f21346a4a6b1c966e0b797f0",
            "title": "Introducing AEVO (AEVO) on Binance Launchpool! Farm AEVO by Staking BNB and FDUSD",
            "type": 1,
            "releaseDate": 1709720755241
          },
          {
            "id": 193626,
            "code": "cfb53ea0b3164637b4d32a075e967d31",
            "title": "Binance Adds Dogwifhat (WIF) on Earn, Convert & Margin",
            "type": 1,
            "releaseDate": 1709652007053
          },
          {
            "id": 193543,
            "code": "90ad67fe5be7483ea058191bfde677e4",
            "title": "Binance Will List Dogwifhat (WIF) with Seed Tag Applied",
            "type": 1,
            "releaseDate": 1709632897364
          },
          {
            "id": 193509,
            "code": "aa4f26d44f5546c5b6695533b2e9279a",
            "title": "Binance Futures Will Launch MYROUSDT and 1000PEPEUSDC Perpetual Contracts With Up to 50x Leverage",
            "type": 1,
            "releaseDate": 1709616923762
          },
          {
            "id": 193491,
            "code": "fb2941dfefc441ad8cc6c6109fdeee8b",
            "title": "Binance Copy Trading Adds New USDⓈ-M Contracts (2024-03-05)",
            "type": 1,
            "releaseDate": 1709608503469
          },
          {
            "id": 193395,
            "code": "b2cc7b70220b45cc8a9daf7e47ed5997",
            "title": "Notice on New Trading Pairs on Binance Spot - 2024-03-05",
            "type": 1,
            "releaseDate": 1709538945082
          },
          {
            "id": 193208,
            "code": "4ec6916d881444c0949ab906352043cc",
            "title": "Binance Adds Axelar (AXL) on Earn, Convert, Margin & Futures",
            "type": 1,
            "releaseDate": 1709296113334
          },
          {
            "id": 193153,
            "code": "2eb66d061d214c31a096cff35ede9360",
            "title": "Binance Will List Axelar (AXL) with Seed Tag Applied",
            "type": 1,
            "releaseDate": 1709277537028
          },
          {
            "id": 193112,
            "code": "57bb7f41d63a44b090b27c3df483344b",
            "title": "Binance Futures Will Launch USDⓈ-M TON Perpetual Contract With Up to 50x Leverage",
            "type": 1,
            "releaseDate": 1709269504921
          },
          {
            "id": 192974,
            "code": "0c9f51c7f9a14266a2ee85eaf36135d1",
            "title": "Binance Adds Portal (PORTAL) on Earn, Convert, Margin & Futures",
            "type": 1,
            "releaseDate": 1709204383007
          },
          {
            "id": 192814,
            "code": "cc897d1544a341c2ae598f594dd9835c",
            "title": "Binance Margin Adds More FDUSD and USDT Pairs",
            "type": 1,
            "releaseDate": 1709087134343
          },
          {
            "id": 192763,
            "code": "3790dd23e35b4ad38a9fce412cbe301d",
            "title": "Notice on New Trading Pairs & Trading Bots Services on Binance Spot - 2024-02-28",
            "type": 1,
            "releaseDate": 1709024423609
          },
          {
            "id": 192447,
            "code": "a3a805c8038545098c34df652cd35d93",
            "title": "Notice on New Trading Pairs & Trading Bots Services on Binance Spot - 2024-02-23",
            "type": 1,
            "releaseDate": 1708596620824
          },
          {
            "id": 192404,
            "code": "876c56d9ebbb4b7c8857c3ac766fa141",
            "title": "Binance Futures Will Launch USDⓈ-M GLM Perpetual Contract With Up to 50x Leverage",
            "type": 1,
            "releaseDate": 1708574741551
          },
          {
            "id": 192382,
            "code": "32cce2a500ef4af5be01c8edf02977f3",
            "title": "Binance Margin Adds ACM, FIO, IQ & More USDT and USDC Pairs",
            "type": 1,
            "releaseDate": 1708571418267
          },
          {
            "id": 192296,
            "code": "0620f90f55f2420b89158808380b6c9d",
            "title": "Introducing Portal (PORTAL) on Binance Launchpool! Farm PORTAL by Staking BNB and FDUSD",
            "type": 1,
            "releaseDate": 1708501813542
          },
          {
            "id": 192240,
            "code": "521a6a71b21046f2b07b021edfd41b9f",
            "title": "Binance Futures Will Launch USDⓈ-M MAVIA Perpetual Contract With Up to 50x Leverage",
            "type": 1,
            "releaseDate": 1708491029077
          },
          {
            "id": 192126,
            "code": "dd8e180b94c84d53a5a93f7b99d1bd08",
            "title": "Binance Options Will Launch T+4 BTCUSDT Daily Options",
            "type": 1,
            "releaseDate": 1708412705927
          },
          {
            "id": 192059,
            "code": "cb15311b17c440d0b0cf077a9b9979a3",
            "title": "Binance Will List Starknet (STRK) with Seed Tag Applied",
            "type": 1,
            "releaseDate": 1708395922135
          },
          {
            "id": 191961,
            "code": "3ebaf75d84274f799dcf28e666c478d9",
            "title": "Binance Adds Pixels (PIXEL) on Earn, Convert, Margin & Futures",
            "type": 1,
            "releaseDate": 1708340422556
          },
          {
            "id": 191907,
            "code": "f5317e4c17a14f0c822441904dc9ae3c",
            "title": "Binance Futures Will Launch USDC-Margined ORDI Perpetual Contract With Up to 75x Leverage",
            "type": 1,
            "releaseDate": 1708327504879
          },
          {
            "id": 191520,
            "code": "3c1eb1074e1b4555ad73eb33734e8541",
            "title": "Binance Futures Will Launch USDC-Margined LINK Perpetual Contract With Up to 75x Leverage",
            "type": 1,
            "releaseDate": 1707901821297
          },
          {
            "id": 191434,
            "code": "8a72fa2ab4cd474f8e5d62c6158eaeef",
            "title": "Binance Futures Will Launch USDⓈ-M OM Perpetual Contract With Up to 50x Leverage",
            "type": 1,
            "releaseDate": 1707801308559
          },
          {
            "id": 191240,
            "code": "c055fa89dda84402b7b662f13b80fffe",
            "title": "Introducing Pixels (PIXEL) on Binance Launchpool! Farm PIXEL by Staking BNB and FDUSD",
            "type": 1,
            "releaseDate": 1707359753017
          },
          {
            "id": 191174,
            "code": "f5602f51a5fe46e6bff70e741ab02df5",
            "title": "Binance Adds Dymension (DYM) on Margin & Futures",
            "type": 1,
            "releaseDate": 1707285913249
          },
          {
            "id": 191009,
            "code": "00095277601046a38159f649b5f0e55b",
            "title": "Binance Will List Dymension (DYM) with Seed Tag Applied",
            "type": 1,
            "releaseDate": 1707211617933
          },
          {
            "id": 190993,
            "code": "b73b590d0ccc4501b49b4ac688ade357",
            "title": "Binance Futures Will Launch USDC-Margined SUI Perpetual Contract With Up to 50x Leverage",
            "type": 1,
            "releaseDate": 1707210078405
          },
          {
            "id": 190925,
            "code": "75f3297929f94cd1af9e378a775360a6",
            "title": "Notice on New Trading Pairs & Trading Bots Services on Binance Spot - 2024-02-07",
            "type": 1,
            "releaseDate": 1707199539841
          },
          {
            "id": 190813,
            "code": "98684ea54d8145c98d86bf80a723c00f",
            "title": "Binance Adds Ronin (RONIN) on Earn, Convert, Margin & Futures",
            "type": 1,
            "releaseDate": 1707143521999
          },
          {
            "id": 190767,
            "code": "dfea1e2ae7fd475196b215e673193c63",
            "title": "Binance Will List Ronin (RONIN) with Seed Tag Applied",
            "type": 1,
            "releaseDate": 1707124296210
          },
          {
            "id": 190693,
            "code": "ff5230c2b9fd41d98dac5cb5aa75909a",
            "title": "Binance Adds Pyth Network (PYTH) on Earn, Convert & Margin",
            "type": 1,
            "releaseDate": 1706880006052
          },
          {
            "id": 190521,
            "code": "f36074f9caa6474fa44fdb18503183d6",
            "title": "Binance Will List Pyth Network (PYTH) with Seed Tag Applied",
            "type": 1,
            "releaseDate": 1706860207072
          },
          {
            "id": 190559,
            "code": "5df2fbaa6747450b943dfa1361fbe19f",
            "title": "Binance Margin Adds CREAM, IRIS & More FDUSD and USDC Pairs",
            "type": 1,
            "releaseDate": 1706857203654
          },
          {
            "id": 190486,
            "code": "527d78a22905461f84c8c85e8b938d4d",
            "title": "Binance Futures Will Launch USDⓈ-M ZETA Perpetual Contract With Up to 50x Leverage",
            "type": 1,
            "releaseDate": 1706847302780
          },
          {
            "id": 190392,
            "code": "3eb7a6881fda4aa795b8d415442d5e79",
            "title": "Notice on New Trading Pairs & Trading Bots Services on Binance Spot - 2024-02-02",
            "type": 1,
            "releaseDate": 1706771740937
          },
          {
            "id": 190315,
            "code": "63ee70ab6e1541a59c8c4e45660fb82d",
            "title": "Binance Adds Jupiter (JUP) on Earn, Convert, Margin & Futures",
            "type": 1,
            "releaseDate": 1706719222049
          },
          {
            "id": 190187,
            "code": "7b5c643c3d8a4c9a9d443b1ceefb0015",
            "title": "Binance Will List Jupiter (JUP) with Seed Tag Applied",
            "type": 1,
            "releaseDate": 1706684813622
          }
        ],
        "catalogs": []
      }
    ]
  },
  "success": true
}