{
  "code": "000000",
  "message": null,
  "messageDetail": null,
  "data": {
    "id": 213198,
    "title": "Binance Will List EigenLayer (EIGEN) with Seed Tag Applied",
    "body": "{\"node\":\"root\",\"child\":[{\"node\":\"element\",\"tag\":\"p\",\"attr\":{\"data-block-id\":\"1cc2b1f8-ef4a-407d-ad28-51f0a275767e\"},\"child\":[{\"node\":\"element\",\"tag\":\"span\",\"attr\":{\"style\":[\"color:\",\"rgb(255,\",\"0,\",\"0)\"]},\"child\":[{\"node\":\"text\",\"text\":\"Note: Please do your own research before making any trades for the aforementioned token \"}]},{\"node\":\"element\",\"tag\":\"strong\",\"child\":[{\"node\":\"element\",\"tag\":\"span\",\"attr\":{\"style\":[\"color:\",\"rgb(255,\",\"0,\",\"0)\"]},\"child\":[{\"node\":\"text\",\"text\":\"outside Binance\"}]}]},{\"node\":\"element\",\"tag\":\"span\",\"attr\":{\"style\":[\"color:\",\"rgb(255,\",\"0,\",\"0)\"]},\"child\":[{\"node\":\"text\",\"text\":\" to avoid any scams and ensure safety of your funds.\"}]}]},{\"node\":\"element\",\"tag\":\"p\",\"attr\":{\"data-block-id\":\"961c9c84-18f4-462f-a1c2-8a23d2c99aad\"},\"child\":[{\"node\":\"element\",\"tag\":\"span\",\"attr\":{\"style\":[\"color:\",\"rgb(0,\",\"0,\",\"0)\"]},\"child\":[{\"node\":\"text\",\"text\":\"&nbsp;\"}]},{\"node\":\"element\",\"tag\":\"strong\",\"child\":[{\"node\":\"element\",\"tag\":\"span\",\"attr\":{\"style\":[\"color:\",\"rgb(0,\",\"0,\",\"0)\"]},\"child\":[{\"node\":\"text\",\"text\":\"Fellow Binancians,\"}]}]}]},{\"node\":\"element\",\"tag\":\"p\",\"attr\":{\"data-block-id\":\"bdf39028-b3dc-4c99-892d-21ab99db0dcc\"},\"child\":[{\"node\":\"element\",\"tag\":\"span\",\"attr\":{\"style\":[\"color:\",\"rgb(30,\",\"35,\",\"41)\"]},\"child\":[{\"node\":\"text\",\"text\":\"Binance will list \"}]},{\"node\":\"element\",\"tag\":\"strong\",\"child\":[{\"node\":\"element\",\"tag\":\"span\",\"attr\":{\"style\":[\"color:\",\"rgb(0,\",\"0,\",\"0)\"]},\"child\":[{\"node\":\"text\",\"text\":\"EigenLayer (EIGEN) \"}]}]},{\"node\":\"element\",\"tag\":\"span\",\"attr\":{\"style\":[\"color:\",\"rgb(30,\",\"35,\",\"41)\"]},\"child\":[{\"node\":\"text\",\"text\":\"and open trading for the following spot trading pairs at \"}]},{\"node\":\"element\",\"tag\":\"strong\",\"child\":[{\"node\":\"element\",\"tag\":\"span\",\"attr\":{\"style\":[\"color:\",\"rgb(30,\",\"35,\",\"41)\"]},\"child\":[{\"node\":\"text\",\"text\":\"2024-10-01 05:00 (UTC)\"}]}]},{\"node\":\"element\",\"tag\":\"span\",\"attr\":{\"style\":[\"color:\",\"rgb(0,\",\"0,\",\"0)\"]},\"child\":[{\"node\":\"text\",\"text\":\".\"}]}]},{\"node\":\"element\",\"tag\":\"ul\",\"attr\":{\"data-block-id\":\"59c081d8-d251-4146-85ae-0c16599b056d\"},\"child\":[{\"node\":\"element\",\"tag\":\"li\",\"attr\":{\"data-block-id\":\"70e72894-be74-427d-b4ec-7fc17a510b74\"},\"child\":[{\"node\":\"element\",\"tag\":\"p\",\"attr\":{\"data-block-id\":\"f6042185-d85a-4512-9a5d-f2d3ba0e2261\"},\"child\":[{\"node\":\"element\",\"tag\":\"span\",\"attr\":{\"style\":[\"color:\",\"rgb(30,\",\"35,\",\"41)\"]},\"child\":[{\"node\":\"text\",\"text\":\"New Spot Trading Pairs: EIGEN/BTC, EIGEN/USDT, EIGEN/FDUSD, and EIGEN/TRY.\"}]}]}]},{\"node\":\"element\",\"tag\":\"li\",\"attr\":{\"data-block-id\":\"bae728f3-36f4-40e4-91a3-b2df25e36538\"},\"child\":[{\"node\":\"element\",\"tag\":\"p\",\"attr\":{\"data-block-id\":\"7a5342db-d882-4f35-89cd-093e7e5a9dd2\"},\"child\":[{\"node\":\"element\",\"tag\":\"span\",\"attr\":{\"style\":[\"color:\",\"rgb(0,\",\"0,\",\"0)\"]},\"child\":[{\"node\":\"text\",\"text\":\"Users can now start depositing \"}]},{\"node\":\"element\",\"tag\":\"a\",\"attr\":{\"target\":\"_blank\",\"rel\":[\"noopener\",\"noreferrer\",\"nofollow\"],\"appurl\":\"0\",\"href\":\"https://www.%suffixOrigin%/%locale%/my/wallet/exchange/deposit/crypto/%20EIGEN\",\"customevents\":[\"[object\",\"Object]\"]},\"child\":[{\"node\":\"element\",\"tag\":\"span\",\"attr\":{\"style\":[\"color:\",\"rgb(17,\",\"85,\",\"204)\"]},\"child\":[{\"node\":\"element\",\"tag\":\"u\",\"child\":[{\"node\":\"text\",\"text\":\"EIGEN\"}]}]}]},{\"node\":\"element\",\"tag\":\"span\",\"attr\":{\"style\":[\"color:\",\"rgb(0,\",\"0,\",\"0)\"]},\"child\":[{\"node\":\"text\",\"text\":\" in preparation for trading\"}]},{\"node\":\"element\",\"tag\":\"span\",\"attr\":{\"style\":[\"color:\",\"rgb(30,\",\"35,\",\"41)\"]},\"child\":[{\"node\":\"text\",\"text\":\".\"}]}]}]},{\"node\":\"element\",\"tag\":\"li\",\"attr\":{\"data-block-id\":\"70762957-5453-4abf-9a77-daed40aa29c9\"},\"child\":[{\"node\":\"element\",\"tag\":\"p\",\"attr\":{\"data-block-id\":\"d7d47c1c-37f0-476d-885b-00841a706d21\"},\"child\":[{\"node\":\"element\",\"tag\":\"span\",\"attr\":{\"style\":[\"color:\",\"rgb(30,\",\"35,\",\"41)\"]},\"child\":[{\"node\":\"text\",\"text\":\"Withdrawals will open at \"}]},{\"node\":\"element\",\"tag\":\"strong\",\"child\":[{\"node\":\"element\",\"tag\":\"span\",\"attr\":{\"style\":[\"color:\",\"rgb(30,\",\"35,\",\"41)\"]},\"child\":[{\"node\":\"text\",\"text\":\"2024-10-02 05:00 (UTC)\"}]}]},{\"node\":\"element\",\"tag\":\"span\",\"attr\":{\"style\":[\"color:\",\"rgb(30,\",\"35,\",\"41)\"]},\"child\":[{\"node\":\"text\",\"text\":\".\"}]}]}]},{\"node\":\"element\",\"tag\":\"li\",\"attr\":{\"data-block-id\":\"e51b89e3-f5c6-4665-839a-0e0175a4682c\"},\"child\":[{\"node\":\"element\",\"tag\":\"p\",\"attr\":{\"data-block-id\":\"b189e2b6-23eb-484b-a880-b1f08d5b687e\"},\"child\":[{\"node\":\"element\",\"tag\":\"span\",\"attr\":{\"style\":[\"color:\",\"rgb(30,\",\"35,\",\"41)\"]},\"child\":[{\"node\":\"text\",\"text\":\"EIGEN Listing Fee: 0 BNB.\"}]}]}]},{\"node\":\"element\",\"tag\":\"li\",\"attr\":{\"data-block-id\":\"0d83c875-9bd2-49e4-b270-c0865915138e\"},\"child\":[{\"node\":\"element\",\"tag\":\"p\",\"attr\":{\"data-block-id\":\"0c130d17-f9a9-4c58-9889-49940f63e54f\"},\"child\":[{\"node\":\"element\",\"tag\":\"a\",\"attr\":{\"target\":\"_blank\",\"rel\":[\"noopener\",\"noreferrer\",\"nofollow\"],\"appurl\":\"\",\"href\":\"https://etherscan.io/address/0xec53bf9167f50cdeb3ae105f56099aaab9061f83\",\"customevents\":[\"[object\",\"Object]\"]},\"child\":[{\"node\":\"element\",\"tag\":\"span\",\"attr\":{\"style\":[\"color:\",\"rgb(17,\",\"85,\",\"204)\"]},\"child\":[{\"node\":\"element\",\"tag\":\"u\",\"child\":[{\"node\":\"text\",\"text\":\"EIGEN Smart Contract Address (ERC20)\"}]}]}]},{\"node\":\"element\",\"tag\":\"span\",\"attr\":{\"style\":[\"color:\",\"rgb(30,\",\"35,\",\"41)\"]},\"child\":[{\"node\":\"text\",\"text\":\" \"}]},{\"node\":\"element\",\"tag\":\"span\",\"attr\":{\"style\":[\"color:\",\"rgb(0,\",\"0,\",\"0)\"]},\"child\":[{\"node\":\"text\",\"text\":\": 0xec53bF9167f50cDEB3Ae105f56099aaaB9061F83\"}]}]}]}]},{\"node\":\"element\",\"tag\":\"p\",\"attr\":{\"data-block-id\":\"bc01a7f4-1c73-43b8-a388-bd2e85ad3914\"},\"child\":[{\"node\":\"element\",\"tag\":\"strong\",\"child\":[{\"node\":\"element\",\"tag\":\"span\",\"attr\":{\"style\":[\"color:\",\"rgb(0,\",\"0,\",\"0)\"]},\"child\":[{\"node\":\"text\",\"text\":\"Notes:\"}]}]}]},{\"node\":\"element\",\"tag\":\"ul\",\"attr\":{\"data-block-id\":\"09eab2c7-c061-41a1-9f42-e9b9dce2170f\"},\"child\":[{\"node\":\"element\",\"tag\":\"li\",\"attr\":{\"data-block-id\":\"08f24dc0-c3ff-4399-8bf0-f6954f18b746\"},\"child\":[{\"node\":\"element\",\"tag\":\"p\",\"attr\":{\"data-block-id\":\"070829fd-839d-430f-a46a-5e686fef9e1b\"},\"child\":[{\"node\":\"element\",\"tag\":\"span\",\"attr\":{\"style\":[\"color:\",\"rgb(0,\",\"0,\",\"0)\"]},\"child\":[{\"node\":\"text\",\"text\":\"The \"}]},{\"node\":\"element\",\"tag\":\"a\",\"attr\":{\"target\":\"_blank\",\"rel\":[\"noopener\",\"noreferrer\",\"nofollow\"],\"appurl\":\"\",\"href\":\"https://www.%suffixOrigin%/%locale%/support/announcement/introducing-seed-tags-monitoring-tags-for-tokens-with-high-volatility-and-risks-b0f241491d0e4d75aa2f8752b7bf8af5\",\"customevents\":[\"[object\",\"Object]\"]},\"child\":[{\"node\":\"element\",\"tag\":\"span\",\"attr\":{\"style\":[\"color:\",\"rgb(17,\",\"85,\",\"204)\"]},\"child\":[{\"node\":\"element\",\"tag\":\"u\",\"child\":[{\"node\":\"text\",\"text\":\"seed tag\"}]}]}]},{\"node\":\"element\",\"tag\":\"span\",\"attr\":{\"style\":[\"color:\",\"rgb(0,\",\"0,\",\"0)\"]},\"child\":[{\"node\":\"text\",\"text\":\" will be applied to EIGEN.\"}]}]}]},{\"node\":\"element\",\"tag\":\"li\",\"attr\":{\"data-block-id\":\"65aad1b5-f6a3-4adb-bb37-bb6a3fc72c22\"},\"child\":[{\"node\":\"element\",\"tag\":\"p\",\"attr\":{\"data-block-id\":\"2f7496d5-a572-4618-a2af-eb7436cd653a\"},\"child\":[{\"node\":\"element\",\"tag\":\"span\",\"attr\":{\"style\":[\"color:\",\"rgb(0,\",\"0,\",\"0)\"]},\"child\":[{\"node\":\"text\",\"text\":\"TRY is a fiat currency and does not represent any other digital currencies.\"}]}]}]},{\"node\":\"element\",\"tag\":\"li\",\"attr\":{\"data-block-id\":\"1f72af59-606c-42d9-bedc-bb0e6cbf8f1c\"},\"child\":[{\"node\":\"element\",\"tag\":\"p\",\"attr\":{\"data-block-id\":\"d0442066-9c3a-4e66-b750-252681398f8b\"},\"child\":[{\"node\":\"element\",\"tag\":\"span\",\"attr\":{\"style\":[\"color:\",\"rgb(0,\",\"0,\",\"0)\"]},\"child\":[{\"node\":\"text\",\"text\":\"The withdrawal open time is an estimated time for users’ reference. Users can view the actual status of withdrawals on the withdrawal page.\"}]}]}]},{\"node\":\"element\",\"tag\":\"li\",\"attr\":{\"data-block-id\":\"f8cacbd1-3307-420e-ad57-bc64cd0dc6f7\"},\"child\":[{\"node\":\"element\",\"tag\":\"p\",\"attr\":{\"data-block-id\":\"0b5d70ad-9342-481b-b6bb-541051f4a848\"},\"child\":[{\"node\":\"element\",\"tag\":\"span\",\"attr\":{\"style\":[\"color:\",\"rgb(0,\",\"0,\",\"0)\"]},\"child\":[{\"node\":\"text\",\"text\":\"Trading Bots &amp; Spot Copy Trading will be enabled for the aforementioned token within 24 hours of it being listed on Spot. For users with running Spot Copy Trading portfolios, pairs can be included by enabling them in the [Personal Pair Preference] section of the Spot Copy Trading settings.\"}]}]}]},{\"node\":\"element\",\"tag\":\"li\",\"attr\":{\"data-block-id\":\"a4a4fd58-8171-44bf-84b9-66462dd04bae\"},\"child\":[{\"node\":\"element\",\"tag\":\"p\",\"attr\":{\"data-block-id\":\"60e58434-058c-4ffe-a994-70b5da27aa0d\"},\"child\":[{\"node\":\"element\",\"tag\":\"span\",\"attr\":{\"style\":[\"color:\",\"rgb(0,\",\"0,\",\"0)\"]},\"child\":[{\"node\":\"text\",\"text\":\"There may be discrepancies in the translated version of this original article in English. Please reference this original version for the latest or most accurate information where any discrepancies may arise.\"}]},{\"node\":\"element\",\"tag\":\"span\",\"child\":[{\"node\":\"text\",\"text\":\"\\t\"}]}]}]}]},{\"node\":\"element\",\"tag\":\"h3\",\"attr\":{\"data-block-id\":\"c8636411-563b-4748-830b-42a5c5314a96\"},\"child\":[{\"node\":\"element\",\"tag\":\"span\",\"attr\":{\"style\":[\"color:\",\"rgb(67,\",\"67,\",\"67)\"]},\"child\":[{\"node\":\"text\",\"text\":\"What Is EigenLayer (EIGEN)\"}]}]},{\"node\":\"element\",\"tag\":\"p\",\"attr\":{\"data-block-id\":\"0dd02ea0-5576-4315-88ec-be3f47591c5a\"},\"child\":[{\"node\":\"element\",\"tag\":\"span\",\"attr\":{\"style\":[\"color:\",\"rgb(0,\",\"0,\",\"0)\"]},\"child\":[{\"node\":\"text\",\"text\":\"EigenLayer is a protocol built on Ethereum that introduces restaking, a new primitive in cryptoeconomic security. This primitive enables the reuse of ETH on the consensus layer.&nbsp;\"}]}]},{\"node\":\"element\",\"tag\":\"h3\",\"attr\":{\"data-block-id\":\"050fb8b4-781e-4315-96fc-b19fa17f448e\"},\"child\":[{\"node\":\"element\",\"tag\":\"strong\",\"child\":[{\"node\":\"element\",\"tag\":\"span\",\"attr\":{\"style\":[\"color:\",\"rgb(67,\",\"67,\",\"67)\"]},\"child\":[{\"node\":\"text\",\"text\":\"Important Notes\"}]}]}]},{\"node\":\"element\",\"tag\":\"ul\",\"attr\":{\"data-block-id\":\"f2287a83-e308-4ce9-8a09-e1011bff4f78\"},\"child\":[{\"node\":\"element\",\"tag\":\"li\",\"attr\":{\"data-block-id\":\"0118ff02-8213-4dcf-b796-2499ea0765d8\"},\"child\":[{\"node\":\"element\",\"tag\":\"p\",\"attr\":{\"data-block-id\":\"3241c4c7-daac-40c9-b354-b7986c217b2d\"},\"child\":[{\"node\":\"element\",\"tag\":\"span\",\"attr\":{\"style\":[\"color:\",\"rgb(0,\",\"0,\",\"0)\"]},\"child\":[{\"node\":\"text\",\"text\":\"EIGEN is a relatively new token that poses a higher than normal risk, and will likely be subject to high price volatility. Users must exercise sufficient risk management and DYOR (do your own research) to fully understand the project before opting to trade the token.\"}]}]}]},{\"node\":\"element\",\"tag\":\"li\",\"attr\":{\"data-block-id\":\"7ce3c483-342c-40ec-a606-77e403acb0a8\"},\"child\":[{\"node\":\"element\",\"tag\":\"p\",\"attr\":{\"data-block-id\":\"53dd5c96-a1f8-4e99-b558-861ede7cba23\"},\"child\":[{\"node\":\"element\",\"tag\":\"a\",\"attr\":{\"target\":\"_blank\",\"rel\":[\"noopener\",\"noreferrer\",\"nofollow\"],\"appurl\":\"\",\"href\":\"https://www.%suffixOrigin%/%locale%/support/announcement/introducing-seed-tags-monitoring-tags-for-tokens-with-high-volatility-and-risks-b0f241491d0e4d75aa2f8752b7bf8af5\",\"customevents\":[\"[object\",\"Object]\"]},\"child\":[{\"node\":\"element\",\"tag\":\"span\",\"attr\":{\"style\":[\"color:\",\"rgb(5,\",\"99,\",\"193)\"]},\"child\":[{\"node\":\"element\",\"tag\":\"u\",\"child\":[{\"node\":\"text\",\"text\":\"Seed tags\"}]}]}]},{\"node\":\"element\",\"tag\":\"span\",\"attr\":{\"style\":[\"color:\",\"rgb(30,\",\"35,\",\"41)\"]},\"child\":[{\"node\":\"text\",\"text\":\" represent \"}]},{\"node\":\"element\",\"tag\":\"strong\",\"child\":[{\"node\":\"element\",\"tag\":\"span\",\"attr\":{\"style\":[\"color:\",\"rgb(30,\",\"35,\",\"41)\"]},\"child\":[{\"node\":\"text\",\"text\":\"innovative projects \"}]}]},{\"node\":\"element\",\"tag\":\"span\",\"attr\":{\"style\":[\"color:\",\"rgb(30,\",\"35,\",\"41)\"]},\"child\":[{\"node\":\"text\",\"text\":\"that\"}]},{\"node\":\"element\",\"tag\":\"strong\",\"child\":[{\"node\":\"element\",\"tag\":\"span\",\"attr\":{\"style\":[\"color:\",\"rgb(30,\",\"35,\",\"41)\"]},\"child\":[{\"node\":\"text\",\"text\":\" may exhibit higher volatility and risks\"}]}]},{\"node\":\"element\",\"tag\":\"span\",\"attr\":{\"style\":[\"color:\",\"rgb(30,\",\"35,\",\"41)\"]},\"child\":[{\"node\":\"text\",\"text\":\" compared to other listed tokens. Seed tag will be applied to EIGEN.\"}]}]}]},{\"node\":\"element\",\"tag\":\"li\",\"attr\":{\"data-block-id\":\"3101465b-6727-4c4e-8294-bb3ae2052dbc\"},\"child\":[{\"node\":\"element\",\"tag\":\"p\",\"attr\":{\"data-block-id\":\"9921e2e8-7944-46e7-bcfb-9266b485bb26\"},\"child\":[{\"node\":\"element\",\"tag\":\"span\",\"attr\":{\"style\":[\"color:\",\"rgb(30,\",\"35,\",\"41)\"]},\"child\":[{\"node\":\"text\",\"text\":\"To gain trading access to tokens marked with seed tag, users will need to pass the corresponding quizzes \"}]},{\"node\":\"element\",\"tag\":\"strong\",\"child\":[{\"node\":\"element\",\"tag\":\"span\",\"attr\":{\"style\":[\"color:\",\"rgb(30,\",\"35,\",\"41)\"]},\"child\":[{\"node\":\"text\",\"text\":\"every 90 days\"}]}]},{\"node\":\"element\",\"tag\":\"span\",\"attr\":{\"style\":[\"color:\",\"rgb(30,\",\"35,\",\"41)\"]},\"child\":[{\"node\":\"text\",\"text\":\" on the Binance Spot and/or Binance Margin platforms, and accept the \"}]},{\"node\":\"element\",\"tag\":\"a\",\"attr\":{\"target\":\"_blank\",\"rel\":[\"noopener\",\"noreferrer\",\"nofollow\"],\"appurl\":\"\",\"href\":\"https://www.%suffixOrigin%/%locale%/terms\",\"customevents\":[\"[object\",\"Object]\"]},\"child\":[{\"node\":\"element\",\"tag\":\"span\",\"attr\":{\"style\":[\"color:\",\"rgb(17,\",\"85,\",\"204)\"]},\"child\":[{\"node\":\"element\",\"tag\":\"u\",\"child\":[{\"node\":\"text\",\"text\":\"Terms of Use\"}]}]}]},{\"node\":\"element\",\"tag\":\"span\",\"attr\":{\"style\":[\"color:\",\"rgb(30,\",\"35,\",\"41)\"]},\"child\":[{\"node\":\"text\",\"text\":\". The quizzes are set up to ensure users are aware of the risks before trading the tokens with seed tags. Users may find seed tags on the corresponding Binance Spot and Binance Margin trading pages, as well as on the \"}]},{\"node\":\"element\",\"tag\":\"a\",\"attr\":{\"target\":\"_blank\",\"rel\":[\"noopener\",\"noreferrer\",\"nofollow\"],\"appurl\":\"\",\"href\":\"https://www.%suffixOrigin%/%locale%/markets/overview\",\"customevents\":[\"[object\",\"Object]\"]},\"child\":[{\"node\":\"element\",\"tag\":\"span\",\"attr\":{\"style\":[\"color:\",\"rgb(17,\",\"85,\",\"204)\"]},\"child\":[{\"node\":\"element\",\"tag\":\"u\",\"child\":[{\"node\":\"text\",\"text\":\"Markets Overview\"}]}]}]},{\"node\":\"element\",\"tag\":\"span\",\"attr\":{\"style\":[\"color:\",\"rgb(30,\",\"35,\",\"41)\"]},\"child\":[{\"node\":\"text\",\"text\":\" page. A risk warning banner will also be displayed for all tokens with seed tags.&nbsp;\"}]}]}]}]},{\"node\":\"element\",\"tag\":\"h3\",\"attr\":{\"data-block-id\":\"b691ec5f-252c-433b-9718-e568712bdcf9\"},\"child\":[{\"node\":\"element\",\"tag\":\"span\",\"attr\":{\"style\":[\"color:\",\"rgb(67,\",\"67,\",\"67)\"]},\"child\":[{\"node\":\"text\",\"text\":\"Additional Information\"}]}]},{\"node\":\"element\",\"tag\":\"ul\",\"attr\":{\"data-block-id\":\"4b0ae573-7ab7-4504-9216-8d306c5d6f24\"},\"child\":[{\"node\":\"element\",\"tag\":\"li\",\"attr\":{\"data-block-id\":\"558a804c-a4fc-4f4e-b34b-ae0b5422bace\"},\"child\":[{\"node\":\"element\",\"tag\":\"p\",\"attr\":{\"data-block-id\":\"8f84aebf-d8c4-4b1c-b93c-2dd166ac9e4e\"},\"child\":[{\"node\":\"element\",\"tag\":\"a\",\"attr\":{\"target\":\"_blank\",\"rel\":[\"noopener\",\"noreferrer\",\"nofollow\"],\"appurl\":\"\",\"href\":\"https://www.eigenlayer.xyz/\",\"customevents\":[\"[object\",\"Object]\"]},\"child\":[{\"node\":\"element\",\"tag\":\"span\",\"attr\":{\"style\":[\"color:\",\"rgb(17,\",\"85,\",\"204)\"]},\"child\":[{\"node\":\"element\",\"tag\":\"u\",\"child\":[{\"node\":\"text\",\"text\":\"EigenLayer Website\"}]}]}]}]}]},{\"node\":\"element\",\"tag\":\"li\",\"attr\":{\"data-block-id\":\"00e3e21a-2878-4c81-b481-3c1bef71ade9\"},\"child\":[{\"node\":\"element\",\"tag\":\"p\",\"attr\":{\"data-block-id\":\"7f7a1719-ff8a-44bc-920b-39f3ca216d30\"},\"child\":[{\"node\":\"element\",\"tag\":\"a\",\"attr\":{\"target\":\"_blank\",\"rel\":[\"noopener\",\"noreferrer\",\"nofollow\"],\"appurl\":\"\",\"href\":\"https://x.com/eigenlayer\",\"customevents\":[\"[object\",\"Object]\"]},\"child\":[{\"node\":\"element\",\"tag\":\"span\",\"attr\":{\"style\":[\"color:\",\"rgb(17,\",\"85,\",\"204)\"]},\"child\":[{\"node\":\"element\",\"tag\":\"u\",\"child\":[{\"node\":\"text\",\"text\":\"EigenLayer X\"}]}]}]}]}]},{\"node\":\"element\",\"tag\":\"li\",\"attr\":{\"data-block-id\":\"07f61d5a-16f3-417c-927a-bf01db441d81\"},\"child\":[{\"node\":\"element\",\"tag\":\"p\",\"attr\":{\"data-block-id\":\"08b98acc-1829-4f9b-acbe-dd8b8145175b\"},\"child\":[{\"node\":\"element\",\"tag\":\"a\",\"attr\":{\"target\":\"_blank\",\"rel\":[\"noopener\",\"noreferrer\",\"nofollow\"],\"appurl\":\"\",\"href\":\"https://www.%suffixOrigin%/%locale%/fee/schedule\",\"customevents\":[\"[object\",\"Object]\"]},\"child\":[{\"node\":\"element\",\"tag\":\"span\",\"attr\":{\"style\":[\"color:\",\"rgb(17,\",\"85,\",\"204)\"]},\"child\":[{\"node\":\"element\",\"tag\":\"u\",\"child\":[{\"node\":\"text\",\"text\":\"Binance Trading Fees\"}]}]}]}]}]},{\"node\":\"element\",\"tag\":\"li\",\"attr\":{\"data-block-id\":\"5f44a0ce-03e1-4f89-8ad0-88a76e42c231\"},\"child\":[{\"node\":\"element\",\"tag\":\"p\",\"attr\":{\"data-block-id\":\"09656820-8dd0-412b-87ba-633d39c5bd51\"},\"child\":[{\"node\":\"element\",\"tag\":\"a\",\"attr\":{\"target\":\"_blank\",\"rel\":[\"noopener\",\"noreferrer\",\"nofollow\"],\"appurl\":\"\",\"href\":\"https://www.%suffixOrigin%/%locale%/trade-rule\",\"customevents\":[\"[object\",\"Object]\"]},\"child\":[{\"node\":\"element\",\"tag\":\"span\",\"attr\":{\"style\":[\"color:\",\"rgb(17,\",\"85,\",\"204)\"]},\"child\":[{\"node\":\"element\",\"tag\":\"u\",\"child\":[{\"node\":\"text\",\"text\":\"Binance Trading Rules\"}]}]}]}]}]}]},{\"node\":\"element\",\"tag\":\"p\",\"attr\":{\"data-block-id\":\"0af7db67-c14d-43c4-b5ea-337cde5a7e53\"},\"child\":[{\"node\":\"element\",\"tag\":\"span\",\"attr\":{\"style\":[\"color:\",\"rgb(0,\",\"0,\",\"0)\"]},\"child\":[{\"node\":\"text\",\"text\":\"Trading of the aforementioned new trading pair(s) is subject to eligibility based on the user's country or region of residence. Please note that the list of restricted countries provided below may be changed from time to time, due to mandatory changes in applicable laws and regulations, or other changes relevant to the trading eligibility of these new trading pair(s). Users need to complete account verification to participate in the trading of these new trading pair(s).\"}]}]},{\"node\":\"element\",\"tag\":\"p\",\"attr\":{\"data-block-id\":\"eac2fee3-b307-45f3-91e6-5141d80e38c6\"},\"child\":[{\"node\":\"element\",\"tag\":\"span\",\"attr\":{\"style\":[\"color:\",\"rgb(0,\",\"0,\",\"0)\"]},\"child\":[{\"node\":\"text\",\"text\":\"Currently, users residing in the following countries or regions will not be able to trade the above-mentioned spot trading pairs: Canada, Cuba, Crimea Region, Iran, Netherlands, North Korea, Syria, United States of America and its territories (American Samoa, Guam, Puerto Rico, the Northern Mariana Islands, the U.S. Virgin Islands), and any non-government controlled areas of Ukraine.\"}]}]},{\"node\":\"element\",\"tag\":\"p\",\"attr\":{\"data-block-id\":\"cf66a1cb-0a9a-4850-9c99-41a632bd68fe\"},\"child\":[{\"node\":\"element\",\"tag\":\"strong\",\"child\":[{\"node\":\"element\",\"tag\":\"span\",\"attr\":{\"style\":[\"color:\",\"rgb(0,\",\"0,\",\"0)\"]},\"child\":[{\"node\":\"text\",\"text\":\"Please note that this list may be updated periodically to accommodate changes in legal, regulatory, or other factors.\"}]}]}]},{\"node\":\"element\",\"tag\":\"p\",\"attr\":{\"data-block-id\":\"2359e3fd-1d3d-4012-88ee-7ceed3307042\"},\"child\":[{\"node\":\"element\",\"tag\":\"span\",\"attr\":{\"style\":[\"color:\",\"rgb(0,\",\"0,\",\"0)\"]},\"child\":[{\"node\":\"text\",\"text\":\"&nbsp;Thank you for your support!\"}]}]},{\"node\":\"element\",\"tag\":\"p\",\"attr\":{\"data-block-id\":\"e39df359-9773-4f29-91f9-8137c9724560\"},\"child\":[{\"node\":\"element\",\"tag\":\"span\",\"attr\":{\"style\":[\"color:\",\"rgb(0,\",\"0,\",\"0)\"]},\"child\":[{\"node\":\"text\",\"text\":\"Binance Team\"}]}]},{\"node\":\"element\",\"tag\":\"p\",\"attr\":{\"data-block-id\":\"199e9e90-6ded-4fa3-969e-45c26423ec4f\"},\"child\":[{\"node\":\"element\",\"tag\":\"span\",\"attr\":{\"style\":[\"color:\",\"rgb(0,\",\"0,\",\"0)\"]},\"child\":[{\"node\":\"text\",\"text\":\"2024-09-30\"}]}]}]}",
    "code": "29494a3db1034233b65522b9e122d079",
    "publishDate": 1727684397115,
    "relatedArticles": [
      {
        "id": 275104,
        "code": "94f88766c6c84d68a07f006bc076ba6a",
        "title": "Binance Futures Will Launch OPENAIUSDT USDⓈ-Margined Perpetual Contract Pre-IPO Trading (2026-05-26)",
        "imageLink": null,
        "shortLink": null,
        "body": null,
        "type": 1,
        "catalogId": null,
        "catalogName": null,
        "publishDate": null,
        "footer": null
      },
      {
        "id": 275072,
        "code": "f3a598a5ab4344af993f67a9c3f4544a",
        "title": "Binance Futures Will Launch Multiple USDⓈ-Margined TradFi Perpetual Contracts (2026-05-26)",
        "imageLink": null,
        "shortLink": null,
        "body": null,
        "type": 1,
        "catalogId": null,
        "catalogName": null,
        "publishDate": null,
        "footer": null
      },
      {
        "id": 274888,
        "code": "6b7d36a6472f4f60803a1d048d1c33e8",
        "title": "Binance Will Add Genius Terminal (GENIUS) and OpenGradient (OPG) on Earn, Buy Crypto, Convert, VIP Loan & Margin",
        "imageLink": null,
        "shortLink": null,
        "body": null,
        "type": 1,
        "catalogId": null,
        "catalogName": null,
        "publishDate": null,
        "footer": null
      },
      {
        "id": 274823,
        "code": "4de6272354be421ba51ea042fd273a8d",
        "title": "Binance Will List Genius Terminal (GENIUS) and OpenGradient (OPG) with Seed Tag Applied",
        "imageLink": null,
        "shortLink": null,
        "body": null,
        "type": 1,
        "catalogId": null,
        "catalogName": null,
        "publishDate": null,
        "footer": null
      },
      {
        "id": 274664,
        "code": "8c6cfaeddbd04f1595f658ac1dfbd0e7",
        "title": "Introducing Gensyn (AIGENSYN) on Binance HODLer Airdrops! Earn AIGENSYN With Retroactive BNB Simple Earn Subscriptions",
        "imageLink": null,
        "shortLink": null,
        "body": null,
        "type": 1,
        "catalogId": null,
        "catalogName": null,
        "publishDate": null,
        "footer": null
      }
    ],
    "articleType": 1,
    "firstCatalogName": "New Cryptocurrency Listing",
    "firstCatalogId": 48,
    "secondCatalogName": null,
    "secondCatalogId": null,
    "thirdCatalogName": null,
    "thirdCatalogId": null,
    "seoTitle": "Binance Will List EigenLayer (EIGEN) with Seed Tag Applied",
    "seoKeywords": "",
    "seoDesc": "Binance will list EigenLayer (EIGEN) and open trading for the following spot trading pairs at 2024-10-01 05:00 (UTC).",
    "version": "1",
    "shareCount": 0,
    "riskWarning": "{\"node\":\"root\",\"child\":[{\"node\":\"element\",\"tag\":\"p\",\"child\":[{\"node\":\"element\",\"tag\":\"span\",\"attr\":{\"style\":[\"color:hsl(0,\",\"0%,\",\"60%);\"]},\"child\":[{\"node\":\"text\",\"text\":\"Binance reserves the right in its sole discretion to amend or change or cancel this announcement at any time and for any reasons without prior notice.\"},{\"node\":\"element\",\"tag\":\"strong\",\"child\":[{\"node\":\"text\",\"text\":\"Risk Warning\"}]},{\"node\":\"text\",\"text\":\": Digital asset prices can be volatile. The value of your investment may go down or up and you may not get back the amount invested. You are solely responsible for your investment decisions and Binance is not liable for any losses you may incur. Futures trading, in particular, is subject to high market risk and price volatility. All of your margin balance may be liquidated in the event of adverse price movement. Past performance is not a reliable predictor of future performance. Before trading, you should make an independent assessment of the appropriateness of the transaction in light of your own objectives and circumstances, including the risks and potential benefits. Consult your own advisers, where appropriate. This information should not be construed as financial or investment advice. To learn more about how to protect yourself, visit our\"}]},{\"node\":\"element\",\"tag\":\"span\",\"attr\":{\"style\":\"color:rgb(30,35,41);\"},\"child\":[{\"node\":\"text\",\"text\":\" \"}]},{\"node\":\"element\",\"tag\":\"a\",\"attr\":{\"href\":\"https://www.binance.com/en/futures/responsible-trading\"},\"child\":[{\"node\":\"element\",\"tag\":\"span\",\"attr\":{\"style\":\"color:rgb(201,148,0);\"},\"child\":[{\"node\":\"text\",\"text\":\"Responsible Trading page\"}]}]},{\"node\":\"element\",\"tag\":\"span\",\"attr\":{\"style\":[\"color:hsl(0,\",\"0%,\",\"90%);\"]},\"child\":[{\"node\":\"text\",\"text\":\".\"}]},{\"node\":\"element\",\"tag\":\"span\",\"attr\":{\"style\":[\"color:hsl(0,\",\"0%,\",\"60%);\"]},\"child\":[{\"node\":\"text\",\"text\":\" For more information, see our\"}]},{\"node\":\"element\",\"tag\":\"span\",\"attr\":{\"style\":\"color:rgb(30,35,41);\"},\"child\":[{\"node\":\"text\",\"text\":\" \"}]},{\"node\":\"element\",\"tag\":\"a\",\"attr\":{\"href\":\"https://www.binance.com/en/terms\"},\"child\":[{\"node\":\"element\",\"tag\":\"span\",\"attr\":{\"style\":\"color:rgb(201,148,0);\"},\"child\":[{\"node\":\"text\",\"text\":\"Terms of Use\"}]}]},{\"node\":\"element\",\"tag\":\"span\",\"attr\":{\"style\":\"color:rgb(30,35,41);\"},\"child\":[{\"node\":\"text\",\"text\":\" \"}]},{\"node\":\"element\",\"tag\":\"span\",\"attr\":{\"style\":[\"color:hsl(0,\",\"0%,\",\"60%);\"]},\"child\":[{\"node\":\"text\",\"text\":\"and \"}]},{\"node\":\"element\",\"tag\":\"a\",\"attr\":{\"href\":\"https://www.binance.com/en/risk-warning\"},\"child\":[{\"node\":\"element\",\"tag\":\"span\",\"attr\":{\"style\":\"color:rgb(201,148,0);\"},\"child\":[{\"node\":\"text\",\"text\":\"Risk Warning\"}]}]},{\"node\":\"element\",\"tag\":\"span\",\"attr\":{\"style\":[\"color:hsl(0,\",\"0%,\",\"90%);\"]},\"child\":[{\"node\":\"text\",\"text\":\".\"}]}]},{\"node\":\"element\",\"tag\":\"p\",\"child\":[{\"node\":\"text\",\"text\":\"&nbsp;\"}]},{\"node\":\"element\",\"tag\":\"p\",\"child\":[{\"node\":\"text\",\"text\":\"&nbsp;\"}]}]}",
    "footer": {
      "id": 1262,
      "parentId": 1261,
      "lang": "en",
      "type": "FAQ",
      "createUser": "be***@***.com",
      "updateUser": "an***@***.com",
      "dbCreateTime": 1721365325000,
      "dbModifyTime": 1769762200000,
      "title": "New Listing",
      "content": "<a href=\"https://binance.onelink.me/y874/803c5d7d\">Trade on-the-go with Binance’s crypto trading app (iOS/Android)</a>Find us on <a href=\"https://t.me/binance_announcements\">Telegram</a><a href=\"https://whatsapp.com/channel/0029VarQ6LL6rsQq7nwhmn1y\">WhatsApp</a><a href=\"https://twitter.com/binance\">X</a><a href=\"https://www.facebook.com/binance\">Facebook</a><a href=\"https://www.instagram.com/binance\">Instagram</a><a href=\"https://discord.gg/binanceofficial\">Discord</a>Binance reserves the right in its sole discretion to amend or cancel this announcement at any time and for any reasons without prior notice.Disclaimer: In compliance with MiCA requirements, from 2024-06-30, unauthorized stablecoins are subject to certain restrictions for EEA users. For more information, please click <a href=\"https://www.binance.com/en/support/announcement/mica-stablecoin-rules-implementation-announcement-884c621e335540e0add5fdce31597121\">here</a>. Digital asset prices are subject to high market risk and price volatility. The value of your investment may go down or up, and you may not get back the amount invested. You are solely responsible for your investment decisions and Binance is not liable for any losses you may incur. Past performance is not a reliable predictor of future performance. You should only invest in products you are familiar with and where you understand the risks. You should carefully consider your investment experience, financial situation, investment objectives and risk tolerance and consult an independent financial adviser prior to making any investment. This material should not be construed as financial advice. Spot trading services are provided by Nest Exchange Limited, which is a Recognised Investment Exchange in the Abu Dhabi Global Market and is an exchange authorised and regulated by the Financial Services Regulatory Authority. For the avoidance of doubt, this announcement is an Exchange Notice for the purposes of Binance’s Exchange Rules. For more information, see our <a href=\"https://www.binance.com/en/about-legal/terms\">Terms of Use</a> and <a href=\"https://www.binance.com/en/risk-warning\">Risk Warning</a>.",
      "contentJson": "{\"layout\":{\"root\":[\"ViewInstance0\"],\"ViewInstance0\":[\"74a854cb-e511-4449-aaf8-dcf4337204e5\",\"2ebb18bb-2f9d-405e-9046-c63c9bceb1d1\",\"2d0171fc-cda4-43f3-b538-551995b2423b\",\"19322034-b865-41d1-af5c-8e267ca92a81\",\"7aee00ca-bcb0-4661-beea-ba4767572f9c\",\"eef6af67-9aab-40b7-8ea5-697797f5a1af\"]},\"hash\":{\"ViewInstance0\":{\"id\":\"Fragment\"},\"74a854cb-e511-4449-aaf8-dcf4337204e5\":{\"id\":\"RichTextParagraph\",\"config\":{\"content\":[{\"id\":\"RichTextLink\",\"config\":{\"href\":\"https://binance.onelink.me/y874/803c5d7d\",\"target\":\"_blank\",\"content\":\"Trade on-the-go with Binance’s crypto trading app (iOS/Android)\",\"customEvents\":\"[object Object]\",\"style\":{\"underscore\":true}}}],\"style\":{}}},\"2ebb18bb-2f9d-405e-9046-c63c9bceb1d1\":{\"id\":\"RichTextParagraph\",\"config\":{\"content\":[{\"id\":\"RichTextText\",\"config\":{\"content\":\"Find us on \",\"style\":{}}}],\"style\":{}}},\"2d0171fc-cda4-43f3-b538-551995b2423b\":{\"id\":\"RichTextList\",\"config\":{\"listType\":\"unordered\",\"content\":[{\"id\":\"RichTextListItem\",\"config\":{\"content\":[{\"id\":\"RichTextParagraph\",\"key\":\"662fba73-90bb-4fb9-9f32-a6836376eda9\",\"config\":{\"content\":[{\"id\":\"RichTextLink\",\"config\":{\"href\":\"https://t.me/binance_announcements\",\"target\":\"_blank\",\"content\":\"Telegram\",\"customEvents\":\"[object Object]\",\"style\":{\"underscore\":true}}}],\"style\":{}}}]}},{\"id\":\"RichTextListItem\",\"config\":{\"content\":[{\"id\":\"RichTextParagraph\",\"key\":\"10959503-cb45-4ee0-b582-f861fd3f4df0\",\"config\":{\"content\":[{\"id\":\"RichTextLink\",\"config\":{\"href\":\"https://whatsapp.com/channel/0029VarQ6LL6rsQq7nwhmn1y\",\"target\":\"_blank\",\"content\":\"WhatsApp\",\"customEvents\":\"[object Object]\",\"style\":{\"underscore\":true}}}],\"style\":{}}}]}},{\"id\":\"RichTextListItem\",\"config\":{\"content\":[{\"id\":\"RichTextParagraph\",\"key\":\"d3e58784-bccf-4409-a325-c81b7565f7e8\",\"config\":{\"content\":[{\"id\":\"RichTextLink\",\"config\":{\"href\":\"https://twitter.com/binance\",\"target\":\"_blank\",\"content\":\"X\",\"customEvents\":\"[object Object]\",\"style\":{\"underscore\":true}}}],\"style\":{}}}]}},{\"id\":\"RichTextListItem\",\"config\":{\"content\":[{\"id\":\"RichTextParagraph\",\"key\":\"2856649f-501f-425d-b741-9b444357aba3\",\"config\":{\"content\":[{\"id\":\"RichTextLink\",\"config\":{\"href\":\"https://www.facebook.com/binance\",\"target\":\"_blank\",\"content\":\"Facebook\",\"customEvents\":\"[object Object]\",\"style\":{\"underscore\":true}}}],\"style\":{}}}]}},{\"id\":\"RichTextListItem\",\"config\":{\"content\":[{\"id\":\"RichTextParagraph\",\"key\":\"3960467e-e055-434e-8dbc-833f56c2006f\",\"config\":{\"content\":[{\"id\":\"RichTextLink\",\"config\":{\"href\":\"https://www.instagram.com/binance\",\"target\":\"_blank\",\"content\":\"Instagram\",\"customEvents\":\"[object Object]\",\"style\":{\"underscore\":true}}}],\"style\":{}}}]}},{\"id\":\"RichTextListItem\",\"config\":{\"content\":[{\"id\":\"RichTextParagraph\",\"key\":\"f258f5b8-0968-4c60-8e36-c7fb8ef4c3e3\",\"config\":{\"content\":[{\"id\":\"RichTextLink\",\"config\":{\"href\":\"https://discord.gg/binanceofficial\",\"target\":\"_blank\",\"content\":\"Discord\",\"customEvents\":\"[object Object]\",\"style\":{\"underscore\":true}}}],\"style\":{}}}]}}]}},\"19322034-b865-41d1-af5c-8e267ca92a81\":{\"id\":\"RichTextParagraph\",\"config\":{\"content\":[{\"id\":\"RichTextText\",\"config\":{\"content\":\"Binance reserves the right in its sole discretion to amend or cancel this announcement at any time and for any reasons without prior notice.\",\"style\":{\"italic\":true}}}],\"style\":{}}},\"7aee00ca-bcb0-4661-beea-ba4767572f9c\":{\"id\":\"RichTextParagraph\",\"config\":{\"content\":[{\"id\":\"RichTextText\",\"config\":{\"content\":\"Disclaimer\",\"style\":{\"bold\":true,\"italic\":true}}},{\"id\":\"RichTextText\",\"config\":{\"content\":\": In compliance with MiCA requirements, from 2024-06-30, unauthorized stablecoins are subject to certain restrictions for EEA users. For more information, please click \",\"style\":{\"italic\":true}}},{\"id\":\"RichTextLink\",\"config\":{\"href\":\"https://www.binance.com/en/support/announcement/mica-stablecoin-rules-implementation-announcement-884c621e335540e0add5fdce31597121\",\"target\":\"_blank\",\"content\":\"here\",\"customEvents\":\"[object Object]\",\"style\":{\"italic\":true,\"underscore\":true}}},{\"id\":\"RichTextText\",\"config\":{\"content\":\". \",\"style\":{\"italic\":true}}}],\"style\":{}}},\"eef6af67-9aab-40b7-8ea5-697797f5a1af\":{\"id\":\"RichTextParagraph\",\"config\":{\"content\":[{\"id\":\"RichTextText\",\"config\":{\"content\":\"Digital asset prices are subject to high market risk and price volatility. The value of your investment may go down or up, and you may not get back the amount invested. You are solely responsible for your investment decisions and Binance is not liable for any losses you may incur. Past performance is not a reliable predictor of future performance. You should only invest in products you are familiar with and where you understand the risks. You should carefully consider your investment experience, financial situation, investment objectives and risk tolerance and consult an independent financial adviser prior to making any investment. This material should not be construed as financial advice. Spot trading services are provided by Nest Exchange Limited, which is a Recognised Investment Exchange in the Abu Dhabi Global Market and is an exchange authorised and regulated by the Financial Services Regulatory Authority. For the avoidance of doubt, this announcement is an Exchange Notice for the purposes of Binance’s Exchange Rules. For more information, see our \",\"style\":{\"italic\":true}}},{\"id\":\"RichTextLink\",\"config\":{\"href\":\"https://www.binance.com/en/about-legal/terms\",\"target\":\"_blank\",\"content\":\"Terms of Use\",\"customEvents\":\"[object Object]\",\"style\":{\"italic\":true}}},{\"id\":\"RichTextText\",\"config\":{\"content\":\" and \",\"style\":{\"italic\":true}}},{\"id\":\"RichTextLink\",\"config\":{\"href\":\"https://www.binance.com/en/risk-warning\",\"target\":\"_blank\",\"content\":\"Risk Warning\",\"customEvents\":\"[object Object]\",\"style\":{\"italic\":true}}},{\"id\":\"RichTextText\",\"config\":{\"content\":\".\",\"style\":{\"italic\":true}}}],\"style\":{}}}}}",
      "textOnly": "Trade on-the-go with Binance’s crypto trading app (iOS/Android)Find us on TelegramWhatsAppXFacebookInstagramDiscordBinance reserves the right in its sole discretion to amend or cancel this announcement at any time and for any reasons without prior notice.Disclaimer: In compliance with MiCA requirements, from 2024-06-30, unauthorized stablecoins are subject to certain restrictions for EEA users. For more information, please click here. Digital asset prices are subject to high market risk and price volatility. The value of your investment may go down or up, and you may not get back the amount invested. You are solely responsible for your investment decisions and Binance is not liable for any losses you may incur. Past performance is not a reliable predictor of future performance. You should only invest in products you are familiar with and where you understand the risks. You should carefully consider your investment experience, financial situation, investment objectives and risk tolerance and consult an independent financial adviser prior to making any investment. This material should not be construed as financial advice. Spot trading services are provided by Nest Exchange Limited, which is a Recognised Investment Exchange in the Abu Dhabi Global Market and is an exchange authorised and regulated by the Financial Services Regulatory Authority. For the avoidance of doubt, this announcement is an Exchange Notice for the purposes of Binance’s Exchange Rules. For more information, see our Terms of Use and Risk Warning.",
      "deleted": 1,
      "footStatus": 1,
      "useCount": 0
    },
    "contentJson": "{\"layout\":{\"root\":[\"ViewInstance0\"],\"ViewInstance0\":[\"1cc2b1f8-ef4a-407d-ad28-51f0a275767e\",\"961c9c84-18f4-462f-a1c2-8a23d2c99aad\",\"bdf39028-b3dc-4c99-892d-21ab99db0dcc\",\"59c081d8-d251-4146-85ae-0c16599b056d\",\"bc01a7f4-1c73-43b8-a388-bd2e85ad3914\",\"09eab2c7-c061-41a1-9f42-e9b9dce2170f\",\"c8636411-563b-4748-830b-42a5c5314a96\",\"0dd02ea0-5576-4315-88ec-be3f47591c5a\",\"050fb8b4-781e-4315-96fc-b19fa17f448e\",\"f2287a83-e308-4ce9-8a09-e1011bff4f78\",\"b691ec5f-252c-433b-9718-e568712bdcf9\",\"4b0ae573-7ab7-4504-9216-8d306c5d6f24\",\"0af7db67-c14d-43c4-b5ea-337cde5a7e53\",\"eac2fee3-b307-45f3-91e6-5141d80e38c6\",\"cf66a1cb-0a9a-4850-9c99-41a632bd68fe\",\"2359e3fd-1d3d-4012-88ee-7ceed3307042\",\"e39df359-9773-4f29-91f9-8137c9724560\",\"199e9e90-6ded-4fa3-969e-45c26423ec4f\"]},\"hash\":{\"ViewInstance0\":{\"id\":\"Fragment\"},\"1cc2b1f8-ef4a-407d-ad28-51f0a275767e\":{\"id\":\"RichTextParagraph\",\"config\":{\"content\":[{\"id\":\"RichTextText\",\"config\":{\"content\":\"Note: Please do your own research before making any trades for the aforementioned token \",\"style\":{\"color\":\"rgb(255, 0, 0)\"}}},{\"id\":\"RichTextText\",\"config\":{\"content\":\"outside Binance\",\"style\":{\"bold\":true,\"color\":\"rgb(255, 0, 0)\"}}},{\"id\":\"RichTextText\",\"config\":{\"content\":\" to avoid any scams and ensure safety of your funds.\",\"style\":{\"color\":\"rgb(255, 0, 0)\"}}}],\"style\":{}}},\"961c9c84-18f4-462f-a1c2-8a23d2c99aad\":{\"id\":\"RichTextParagraph\",\"config\":{\"content\":[{\"id\":\"RichTextText\",\"config\":{\"content\":\" \",\"style\":{\"color\":\"rgb(0, 0, 0)\"}}},{\"id\":\"RichTextText\",\"config\":{\"content\":\"Fellow Binancians,\",\"style\":{\"bold\":true,\"color\":\"rgb(0, 0, 0)\"}}}],\"style\":{}}},\"bdf39028-b3dc-4c99-892d-21ab99db0dcc\":{\"id\":\"RichTextParagraph\",\"config\":{\"content\":[{\"id\":\"RichTextText\",\"config\":{\"content\":\"Binance will list \",\"style\":{\"color\":\"rgb(30, 35, 41)\"}}},{\"id\":\"RichTextText\",\"config\":{\"content\":\"EigenLayer (EIGEN) \",\"style\":{\"bold\":true,\"color\":\"rgb(0, 0, 0)\"}}},{\"id\":\"RichTextText\",\"config\":{\"content\":\"and open trading for the following spot trading pairs at \",\"style\":{\"color\":\"rgb(30, 35, 41)\"}}},{\"id\":\"RichTextText\",\"config\":{\"content\":\"2024-10-01 05:00 (UTC)\",\"style\":{\"bold\":true,\"color\":\"rgb(30, 35, 41)\"}}},{\"id\":\"RichTextText\",\"config\":{\"content\":\".\",\"style\":{\"color\":\"rgb(0, 0, 0)\"}}}],\"style\":{}}},\"59c081d8-d251-4146-85ae-0c16599b056d\":{\"id\":\"RichTextList\",\"config\":{\"listType\":\"unordered\",\"content\":[{\"id\":\"RichTextListItem\",\"config\":{\"content\":[{\"id\":\"RichTextParagraph\",\"key\":\"f6042185-d85a-4512-9a5d-f2d3ba0e2261\",\"config\":{\"content\":[{\"id\":\"RichTextText\",\"config\":{\"content\":\"New Spot Trading Pairs: EIGEN/BTC, EIGEN/USDT, EIGEN/FDUSD, and EIGEN/TRY.\",\"style\":{\"color\":\"rgb(30, 35, 41)\"}}}],\"style\":{}}}]}},{\"id\":\"RichTextListItem\",\"config\":{\"content\":[{\"id\":\"RichTextParagraph\",\"key\":\"7a5342db-d882-4f35-89cd-093e7e5a9dd2\",\"config\":{\"content\":[{\"id\":\"RichTextText\",\"config\":{\"content\":\"Users can now start depositing \",\"style\":{\"color\":\"rgb(0, 0, 0)\"}}},{\"id\":\"RichTextLink\",\"config\":{\"href\":\"https://www.%suffixOrigin%/%locale%/my/wallet/exchange/deposit/crypto/%20EIGEN\",\"target\":\"_blank\",\"content\":\"EIGEN\",\"customEvents\":\"[object Object]\",\"style\":{\"color\":\"rgb(17, 85, 204)\",\"underscore\":true}}},{\"id\":\"RichTextText\",\"config\":{\"content\":\" in preparation for trading\",\"style\":{\"color\":\"rgb(0, 0, 0)\"}}},{\"id\":\"RichTextText\",\"config\":{\"content\":\".\",\"style\":{\"color\":\"rgb(30, 35, 41)\"}}}],\"style\":{}}}]}},{\"id\":\"RichTextListItem\",\"config\":{\"content\":[{\"id\":\"RichTextParagraph\",\"key\":\"d7d47c1c-37f0-476d-885b-00841a706d21\",\"config\":{\"content\":[{\"id\":\"RichTextText\",\"config\":{\"content\":\"Withdrawals will open at \",\"style\":{\"color\":\"rgb(30, 35, 41)\"}}},{\"id\":\"RichTextText\",\"config\":{\"content\":\"2024-10-02 05:00 (UTC)\",\"style\":{\"bold\":true,\"color\":\"rgb(30, 35, 41)\"}}},{\"id\":\"RichTextText\",\"config\":{\"content\":\".\",\"style\":{\"color\":\"rgb(30, 35, 41)\"}}}],\"style\":{}}}]}},{\"id\":\"RichTextListItem\",\"config\":{\"content\":[{\"id\":\"RichTextParagraph\",\"key\":\"b189e2b6-23eb-484b-a880-b1f08d5b687e\",\"config\":{\"content\":[{\"id\":\"RichTextText\",\"config\":{\"content\":\"EIGEN Listing Fee: 0 BNB.\",\"style\":{\"color\":\"rgb(30, 35, 41)\"}}}],\"style\":{}}}]}},{\"id\":\"RichTextListItem\",\"config\":{\"content\":[{\"id\":\"RichTextParagraph\",\"key\":\"0c130d17-f9a9-4c58-9889-49940f63e54f\",\"config\":{\"content\":[{\"id\":\"RichTextLink\",\"config\":{\"href\":\"https://etherscan.io/address/0xec53bf9167f50cdeb3ae105f56099aaab9061f83\",\"target\":\"_blank\",\"content\":\"EIGEN Smart Contract Address (ERC20)\",\"customEvents\":{},\"style\":{\"color\":\"rgb(17, 85, 204)\",\"underscore\":true}}},{\"id\":\"RichTextText\",\"config\":{\"content\":\" \",\"style\":{\"color\":\"rgb(30, 35, 41)\"}}},{\"id\":\"RichTextText\",\"config\":{\"content\":\": 0xec53bF9167f50cDEB3Ae105f56099aaaB9061F83\",\"style\":{\"color\":\"rgb(0, 0, 0)\"}}}],\"style\":{}}}]}}]}},\"bc01a7f4-1c73-43b8-a388-bd2e85ad3914\":{\"id\":\"RichTextParagraph\",\"config\":{\"content\":[{\"id\":\"RichTextText\",\"config\":{\"content\":\"Notes:\",\"style\":{\"bold\":true,\"color\":\"rgb(0, 0, 0)\"}}}],\"style\":{}}},\"09eab2c7-c061-41a1-9f42-e9b9dce2170f\":{\"id\":\"RichTextList\",\"config\":{\"listType\":\"unordered\",\"content\":[{\"id\":\"RichTextListItem\",\"config\":{\"content\":[{\"id\":\"RichTextParagraph\",\"key\":\"070829fd-839d-430f-a46a-5e686fef9e1b\",\"config\":{\"content\":[{\"id\":\"RichTextText\",\"config\":{\"content\":\"The \",\"style\":{\"color\":\"rgb(0, 0, 0)\"}}},{\"id\":\"RichTextLink\",\"config\":{\"href\":\"https://www.%suffixOrigin%/%locale%/support/announcement/introducing-seed-tags-monitoring-tags-for-tokens-with-high-volatility-and-risks-b0f241491d0e4d75aa2f8752b7bf8af5\",\"target\":\"_blank\",\"content\":\"seed tag\",\"customEvents\":{},\"style\":{\"color\":\"rgb(17, 85, 204)\",\"underscore\":true}}},{\"id\":\"RichTextText\",\"config\":{\"content\":\" will be applied to EIGEN.\",\"style\":{\"color\":\"rgb(0, 0, 0)\"}}}],\"style\":{}}}]}},{\"id\":\"RichTextListItem\",\"config\":{\"content\":[{\"id\":\"RichTextParagraph\",\"key\":\"2f7496d5-a572-4618-a2af-eb7436cd653a\",\"config\":{\"content\":[{\"id\":\"RichTextText\",\"config\":{\"content\":\"TRY is a fiat currency and does not represent any other digital currencies.\",\"style\":{\"color\":\"rgb(0, 0, 0)\"}}}],\"style\":{}}}]}},{\"id\":\"RichTextListItem\",\"config\":{\"content\":[{\"id\":\"RichTextParagraph\",\"key\":\"d0442066-9c3a-4e66-b750-252681398f8b\",\"config\":{\"content\":[{\"id\":\"RichTextText\",\"config\":{\"content\":\"The withdrawal open time is an estimated time for users’ reference. Users can view the actual status of withdrawals on the withdrawal page.\",\"style\":{\"color\":\"rgb(0, 0, 0)\"}}}],\"style\":{}}}]}},{\"id\":\"RichTextListItem\",\"config\":{\"content\":[{\"id\":\"RichTextParagraph\",\"key\":\"0b5d70ad-9342-481b-b6bb-541051f4a848\",\"config\":{\"content\":[{\"id\":\"RichTextText\",\"config\":{\"content\":\"Trading Bots & Spot Copy Trading will be enabled for the aforementioned token within 24 hours of it being listed on Spot. For users with running Spot Copy Trading portfolios, pairs can be included by enabling them in the [Personal Pair Preference] section of the Spot Copy Trading settings.\",\"style\":{\"color\":\"rgb(0, 0, 0)\"}}}],\"style\":{}}}]}},{\"id\":\"RichTextListItem\",\"config\":{\"content\":[{\"id\":\"RichTextParagraph\",\"key\":\"60e58434-058c-4ffe-a994-70b5da27aa0d\",\"config\":{\"content\":[{\"id\":\"RichTextText\",\"config\":{\"content\":\"There may be discrepancies in the translated version of this original article in English. Please reference this original version for the latest or most accurate information where any discrepancies may arise.\",\"style\":{\"color\":\"rgb(0, 0, 0)\"}}},{\"id\":\"RichTextText\",\"config\":{\"content\":\"\\t\",\"style\":{\"color\":\"\"}}}],\"style\":{}}}]}}]}},\"c8636411-563b-4748-830b-42a5c5314a96\":{\"id\":\"RichTextHeader\",\"config\":{\"tag\":\"h3\",\"content\":[{\"id\":\"RichTextText\",\"config\":{\"content\":\"What Is EigenLayer (EIGEN)\",\"style\":{\"color\":\"rgb(67, 67, 67)\"}}}]}},\"0dd02ea0-5576-4315-88ec-be3f47591c5a\":{\"id\":\"RichTextParagraph\",\"config\":{\"content\":[{\"id\":\"RichTextText\",\"config\":{\"content\":\"EigenLayer is a protocol built on Ethereum that introduces restaking, a new primitive in cryptoeconomic security. This primitive enables the reuse of ETH on the consensus layer. \",\"style\":{\"color\":\"rgb(0, 0, 0)\"}}}],\"style\":{}}},\"050fb8b4-781e-4315-96fc-b19fa17f448e\":{\"id\":\"RichTextHeader\",\"config\":{\"tag\":\"h3\",\"content\":[{\"id\":\"RichTextText\",\"config\":{\"content\":\"Important Notes\",\"style\":{\"bold\":true,\"color\":\"rgb(67, 67, 67)\"}}}]}},\"f2287a83-e308-4ce9-8a09-e1011bff4f78\":{\"id\":\"RichTextList\",\"config\":{\"listType\":\"unordered\",\"content\":[{\"id\":\"RichTextListItem\",\"config\":{\"content\":[{\"id\":\"RichTextParagraph\",\"key\":\"3241c4c7-daac-40c9-b354-b7986c217b2d\",\"config\":{\"content\":[{\"id\":\"RichTextText\",\"config\":{\"content\":\"EIGEN is a relatively new token that poses a higher than normal risk, and will likely be subject to high price volatility. Users must exercise sufficient risk management and DYOR (do your own research) to fully understand the project before opting to trade the token.\",\"style\":{\"color\":\"rgb(0, 0, 0)\"}}}],\"style\":{}}}]}},{\"id\":\"RichTextListItem\",\"config\":{\"content\":[{\"id\":\"RichTextParagraph\",\"key\":\"53dd5c96-a1f8-4e99-b558-861ede7cba23\",\"config\":{\"content\":[{\"id\":\"RichTextLink\",\"config\":{\"href\":\"https://www.%suffixOrigin%/%locale%/support/announcement/introducing-seed-tags-monitoring-tags-for-tokens-with-high-volatility-and-risks-b0f241491d0e4d75aa2f8752b7bf8af5\",\"target\":\"_blank\",\"content\":\"Seed tags\",\"customEvents\":{},\"style\":{\"color\":\"rgb(5, 99, 193)\",\"underscore\":true}}},{\"id\":\"RichTextText\",\"config\":{\"content\":\" represent \",\"style\":{\"color\":\"rgb(30, 35, 41)\"}}},{\"id\":\"RichTextText\",\"config\":{\"content\":\"innovative projects \",\"style\":{\"bold\":true,\"color\":\"rgb(30, 35, 41)\"}}},{\"id\":\"RichTextText\",\"config\":{\"content\":\"that\",\"style\":{\"color\":\"rgb(30, 35, 41)\"}}},{\"id\":\"RichTextText\",\"config\":{\"content\":\" may exhibit higher volatility and risks\",\"style\":{\"bold\":true,\"color\":\"rgb(30, 35, 41)\"}}},{\"id\":\"RichTextText\",\"config\":{\"content\":\" compared to other listed tokens. Seed tag will be applied to EIGEN.\",\"style\":{\"color\":\"rgb(30, 35, 41)\"}}}],\"style\":{}}}]}},{\"id\":\"RichTextListItem\",\"config\":{\"content\":[{\"id\":\"RichTextParagraph\",\"key\":\"9921e2e8-7944-46e7-bcfb-9266b485bb26\",\"config\":{\"content\":[{\"id\":\"RichTextText\",\"config\":{\"content\":\"To gain trading access to tokens marked with seed tag, users will need to pass the corresponding quizzes \",\"style\":{\"color\":\"rgb(30, 35, 41)\"}}},{\"id\":\"RichTextText\",\"config\":{\"content\":\"every 90 days\",\"style\":{\"bold\":true,\"color\":\"rgb(30, 35, 41)\"}}},{\"id\":\"RichTextText\",\"config\":{\"content\":\" on the Binance Spot and/or Binance Margin platforms, and accept the \",\"style\":{\"color\":\"rgb(30, 35, 41)\"}}},{\"id\":\"RichTextLink\",\"config\":{\"href\":\"https://www.%suffixOrigin%/%locale%/terms\",\"target\":\"_blank\",\"content\":\"Terms of Use\",\"customEvents\":{},\"style\":{\"color\":\"rgb(17, 85, 204)\",\"underscore\":true}}},{\"id\":\"RichTextText\",\"config\":{\"content\":\". The quizzes are set up to ensure users are aware of the risks before trading the tokens with seed tags. Users may find seed tags on the corresponding Binance Spot and Binance Margin trading pages, as well as on the \",\"style\":{\"color\":\"rgb(30, 35, 41)\"}}},{\"id\":\"RichTextLink\",\"config\":{\"href\":\"https://www.%suffixOrigin%/%locale%/markets/overview\",\"target\":\"_blank\",\"content\":\"Markets Overview\",\"customEvents\":{},\"style\":{\"color\":\"rgb(17, 85, 204)\",\"underscore\":true}}},{\"id\":\"RichTextText\",\"config\":{\"content\":\" page. A risk warning banner will also be displayed for all tokens with seed tags. \",\"style\":{\"color\":\"rgb(30, 35, 41)\"}}}],\"style\":{}}}]}}]}},\"b691ec5f-252c-433b-9718-e568712bdcf9\":{\"id\":\"RichTextHeader\",\"config\":{\"tag\":\"h3\",\"content\":[{\"id\":\"RichTextText\",\"config\":{\"content\":\"Additional Information\",\"style\":{\"color\":\"rgb(67, 67, 67)\"}}}]}},\"4b0ae573-7ab7-4504-9216-8d306c5d6f24\":{\"id\":\"RichTextList\",\"config\":{\"listType\":\"unordered\",\"content\":[{\"id\":\"RichTextListItem\",\"config\":{\"content\":[{\"id\":\"RichTextParagraph\",\"key\":\"8f84aebf-d8c4-4b1c-b93c-2dd166ac9e4e\",\"config\":{\"content\":[{\"id\":\"RichTextLink\",\"config\":{\"href\":\"https://www.eigenlayer.xyz/\",\"target\":\"_blank\",\"content\":\"EigenLayer Website\",\"customEvents\":{},\"style\":{\"color\":\"rgb(17, 85, 204)\",\"underscore\":true}}}],\"style\":{}}}]}},{\"id\":\"RichTextListItem\",\"config\":{\"content\":[{\"id\":\"RichTextParagraph\",\"key\":\"7f7a1719-ff8a-44bc-920b-39f3ca216d30\",\"config\":{\"content\":[{\"id\":\"RichTextLink\",\"config\":{\"href\":\"https://x.com/eigenlayer\",\"target\":\"_blank\",\"content\":\"EigenLayer X\",\"customEvents\":{},\"style\":{\"color\":\"rgb(17, 85, 204)\",\"underscore\":true}}}],\"style\":{}}}]}},{\"id\":\"RichTextListItem\",\"config\":{\"content\":[{\"id\":\"RichTextParagraph\",\"key\":\"08b98acc-1829-4f9b-acbe-dd8b8145175b\",\"config\":{\"content\":[{\"id\":\"RichTextLink\",\"config\":{\"href\":\"https://www.%suffixOrigin%/%locale%/fee/schedule\",\"target\":\"_blank\",\"content\":\"Binance Trading Fees\",\"customEvents\":{},\"style\":{\"color\":\"rgb(17, 85, 204)\",\"underscore\":true}}}],\"style\":{}}}]}},{\"id\":\"RichTextListItem\",\"config\":{\"content\":[{\"id\":\"RichTextParagraph\",\"key\":\"09656820-8dd0-412b-87ba-633d39c5bd51\",\"config\":{\"content\":[{\"id\":\"RichTextLink\",\"config\":{\"href\":\"https://www.%suffixOrigin%/%locale%/trade-rule\",\"target\":\"_blank\",\"content\":\"Binance Trading Rules\",\"customEvents\":{},\"style\":{\"color\":\"rgb(17, 85, 204)\",\"underscore\":true}}}],\"style\":{}}}]}}]}},\"0af7db67-c14d-43c4-b5ea-337cde5a7e53\":{\"id\":\"RichTextParagraph\",\"config\":{\"content\":[{\"id\":\"RichTextText\",\"config\":{\"content\":\"Trading of the aforementioned new trading pair(s) is subject to eligibility based on the user's country or region of residence. Please note that the list of restricted countries provided below may be changed from time to time, due to mandatory changes in applicable laws and regulations, or other changes relevant to the trading eligibility of these new trading pair(s). Users need to complete account verification to participate in the trading of these new trading pair(s).\",\"style\":{\"color\":\"rgb(0, 0, 0)\"}}}],\"style\":{}}},\"eac2fee3-b307-45f3-91e6-5141d80e38c6\":{\"id\":\"RichTextParagraph\",\"config\":{\"content\":[{\"id\":\"RichTextText\",\"config\":{\"content\":\"Currently, users residing in the following countries or regions will not be able to trade the above-mentioned spot trading pairs: Canada, Cuba, Crimea Region, Iran, Netherlands, North Korea, Syria, United States of America and its territories (American Samoa, Guam, Puerto Rico, the Northern Mariana Islands, the U.S. Virgin Islands), and any non-government controlled areas of Ukraine.\",\"style\":{\"color\":\"rgb(0, 0, 0)\"}}}],\"style\":{}}},\"cf66a1cb-0a9a-4850-9c99-41a632bd68fe\":{\"id\":\"RichTextParagraph\",\"config\":{\"content\":[{\"id\":\"RichTextText\",\"config\":{\"content\":\"Please note that this list may be updated periodically to accommodate changes in legal, regulatory, or other factors.\",\"style\":{\"bold\":true,\"color\":\"rgb(0, 0, 0)\"}}}],\"style\":{}}},\"2359e3fd-1d3d-4012-88ee-7ceed3307042\":{\"id\":\"RichTextParagraph\",\"config\":{\"content\":[{\"id\":\"RichTextText\",\"config\":{\"content\":\" Thank you for your support!\",\"style\":{\"color\":\"rgb(0, 0, 0)\"}}}],\"style\":{}}},\"e39df359-9773-4f29-91f9-8137c9724560\":{\"id\":\"RichTextParagraph\",\"config\":{\"content\":[{\"id\":\"RichTextText\",\"config\":{\"content\":\"Binance Team\",\"style\":{\"color\":\"rgb(0, 0, 0)\"}}}],\"style\":{}}},\"199e9e90-6ded-4fa3-969e-45c26423ec4f\":{\"id\":\"RichTextParagraph\",\"config\":{\"content\":[{\"id\":\"RichTextText\",\"config\":{\"content\":\"2024-09-30\",\"style\":{\"color\":\"rgb(0, 0, 0)\"}}}],\"style\":{}}}}}",
    "pairs": [],
    "lastUpdateTime": 0,
    "releaseDate": 1727684397115
  },
  "success": true
}